diffopt/__init__.py
diffopt/_version.py
diffopt/kdescent/__init__.py
diffopt/kdescent/descent.py
diffopt/kdescent/keygen.py
diffopt/kdescent/kstats.py
diffopt/kdescent/tests/__init__.py
diffopt/kdescent/tests/test_kdescent.py
diffopt/kdescent/tests/test_pretrain.py
diffopt/multigrad/__init__.py
diffopt/multigrad/adam.py
diffopt/multigrad/bfgs.py
diffopt/multigrad/multigrad.py
diffopt/multigrad/util.py
diffopt/multigrad/tests/__init__.py
diffopt/multigrad/tests/test_mpi.py
diffopt/multigrad/tests/smf_example/__init__.py
diffopt/multigrad/tests/smf_example/benchmark.py
diffopt/multigrad/tests/smf_example/smf_grad_descent.py
diffopt/multiswarm/__init__.py
diffopt/multiswarm/mpi_utils.py
diffopt/multiswarm/pso_update.py
diffopt/multiswarm/tests/__init__.py
diffopt/multiswarm/tests/test_pso_update.py
diffopt-2.0.0.dist-info/licenses/LICENSE
diffopt-2.0.0.dist-info/METADATA
diffopt-2.0.0.dist-info/WHEEL
diffopt-2.0.0.dist-info/top_level.txt
diffopt-2.0.0.dist-info/RECORD
