Metadata-Version: 2.4
Name: diffopt
Version: 2.0.0
Summary: Parallelization and optimization of Jax models
Author-email: Alan Pearl <alanpearl13@gmail.com>
License: MIT License
Project-URL: home, https://github.com/AlanPearl/diffopt
Classifier: Programming Language :: Python :: 3
Requires-Python: >=3.10
License-File: LICENSE
Requires-Dist: numpy
Requires-Dist: jax
Requires-Dist: jaxopt
Requires-Dist: optax
Requires-Dist: scipy>=1.15
Requires-Dist: tqdm
Dynamic: license-file
